{
  "width": 3968,
  "height": 2976,
  "ispano": false,
  "objects": [
    {
      "key": "2U3EbJL6Q7eNuB99X_p4yg",
      "label": "other-sign",
      "bbox": {
        "xmin": 2548.78125,
        "ymin": 1161.046875,
        "xmax": 2674.71875,
        "ymax": 1201.0078125
      },
      "properties": {
        "barrier": false,
        "occluded": false,
        "out-of-frame": false,
        "exterior": false,
        "ambiguous": false,
        "included": false,
        "direction-or-information": false,
        "highway": false,
        "dummy": false
      }
    },
    {
      "key": "9ibV7S09TDuZAqaQ0WN5iA",
      "label": "other-sign",
      "bbox": {
        "xmin": 2554.59375,
        "ymin": 1205.3671875,
        "xmax": 2870.40625,
        "ymax": 1276.5703125
      },
      "properties": {
        "barrier": false,
        "occluded": false,
        "out-of-frame": false,
        "exterior": false,
        "ambiguous": false,
        "included": false,
        "direction-or-information": false,
        "highway": false,
        "dummy": false
      }
    },
    {
      "key": "mr58HQMUSwG6sBDeQRdMAw",
      "label": "other-sign",
      "bbox": {
        "xmin": 2062.46875,
        "ymin": 1397.1796875,
        "xmax": 2074.09375,
        "ymax": 1406.625
      },
      "properties": {
        "barrier": false,
        "occluded": false,
        "out-of-frame": false,
        "exterior": false,
        "ambiguous": true,
        "included": false,
        "direction-or-information": false,
        "highway": false,
        "dummy": false
      }
    }
  ]
}