{
  "width": 4032,
  "height": 3024,
  "ispano": false,
  "objects": [
    {
      "key": "QQ8TEntQRb2X7qpcFdCsgQ",
      "label": "regulatory--lane-control--g1",
      "bbox": {
        "xmin": 1817.15625,
        "ymin": 1566.6328125,
        "xmax": 1889.015625,
        "ymax": 1639.72265625
      },
      "properties": {
        "barrier": false,
        "occluded": false,
        "out-of-frame": false,
        "exterior": false,
        "ambiguous": false,
        "included": false,
        "direction-or-information": false,
        "highway": false,
        "dummy": false
      }
    }
  ]
}