{
  "width": 1024,
  "height": 768,
  "ispano": false,
  "objects": [
    {
      "key": "zj8mz2527317euyzc9kibu",
      "label": "warning--traffic-merges-right--g2",
      "bbox": {
        "xmin": 824.5,
        "ymin": 304.3125,
        "xmax": 893.75,
        "ymax": 370.5
      },
      "properties": {
        "barrier": false,
        "occluded": false,
        "out-of-frame": false,
        "exterior": false,
        "ambiguous": false,
        "included": false,
        "direction-or-information": false,
        "highway": false,
        "dummy": false
      }
    },
    {
      "key": "fzdc7yeeh67vcxelsc19vr",
      "label": "regulatory--go-straight--g1",
      "bbox": {
        "xmin": 573.75,
        "ymin": 372.1875,
        "xmax": 590.5,
        "ymax": 388.3125
      },
      "properties": {
        "barrier": false,
        "occluded": false,
        "out-of-frame": false,
        "exterior": false,
        "ambiguous": false,
        "included": false,
        "direction-or-information": false,
        "highway": false,
        "dummy": false
      }
    },
    {
      "key": "4ir039vsls64frybakov4h",
      "label": "other-sign",
      "bbox": {
        "xmin": 308.25,
        "ymin": 372.375,
        "xmax": 321.5,
        "ymax": 385.5
      },
      "properties": {
        "barrier": false,
        "occluded": false,
        "out-of-frame": false,
        "exterior": false,
        "ambiguous": true,
        "included": false,
        "direction-or-information": false,
        "highway": false,
        "dummy": false
      }
    },
    {
      "key": "plsnte62u6i34h8urggn8l",
      "label": "other-sign",
      "bbox": {
        "xmin": 243.0,
        "ymin": 372.75,
        "xmax": 258.75,
        "ymax": 388.5
      },
      "properties": {
        "barrier": false,
        "occluded": false,
        "out-of-frame": false,
        "exterior": false,
        "ambiguous": true,
        "included": false,
        "direction-or-information": false,
        "highway": false,
        "dummy": false
      }
    },
    {
      "key": "np6bnhn8pjjch1nee26nc4",
      "label": "other-sign",
      "bbox": {
        "xmin": 527.25,
        "ymin": 384.5625,
        "xmax": 534.25,
        "ymax": 390.5625
      },
      "properties": {
        "barrier": false,
        "occluded": false,
        "out-of-frame": false,
        "exterior": false,
        "ambiguous": true,
        "included": false,
        "direction-or-information": false,
        "highway": false,
        "dummy": false
      }
    },
    {
      "key": "4rxe85cwhdzi0zmhl699jx",
      "label": "other-sign",
      "bbox": {
        "xmin": 533.0,
        "ymin": 381.9375,
        "xmax": 540.0,
        "ymax": 387.5625
      },
      "properties": {
        "barrier": false,
        "occluded": false,
        "out-of-frame": false,
        "exterior": false,
        "ambiguous": true,
        "included": false,
        "direction-or-information": false,
        "highway": false,
        "dummy": false
      }
    },
    {
      "key": "qys7rw5rd5yayqq3dlw5s2",
      "label": "other-sign",
      "bbox": {
        "xmin": 532.75,
        "ymin": 388.3125,
        "xmax": 539.75,
        "ymax": 394.875
      },
      "properties": {
        "barrier": false,
        "occluded": false,
        "out-of-frame": false,
        "exterior": false,
        "ambiguous": true,
        "included": false,
        "direction-or-information": false,
        "highway": false,
        "dummy": false
      }
    }
  ]
}