{
  "width": 4128,
  "height": 3096,
  "ispano": false,
  "objects": [
    {
      "key": "bty9ej7vgfechfhdcdvbh9",
      "label": "regulatory--maximum-speed-limit-60--g1",
      "bbox": {
        "xmin": 2736.2109375,
        "ymin": 1614.515625,
        "xmax": 2789.625,
        "ymax": 1665.9140625
      },
      "properties": {
        "barrier": false,
        "occluded": false,
        "out-of-frame": false,
        "exterior": false,
        "ambiguous": false,
        "included": false,
        "direction-or-information": false,
        "highway": false,
        "dummy": false
      }
    },
    {
      "key": "8h3xdu15m6rc23o8y0bwiy",
      "label": "information--pedestrians-crossing--g1",
      "bbox": {
        "xmin": 1572.1875,
        "ymin": 1613.759765625,
        "xmax": 1599.3984375,
        "ymax": 1642.482421875
      },
      "properties": {
        "barrier": false,
        "occluded": false,
        "out-of-frame": false,
        "exterior": false,
        "ambiguous": false,
        "included": false,
        "direction-or-information": false,
        "highway": false,
        "dummy": false
      }
    },
    {
      "key": "r2j4baxnv07qsmvfl7vemr",
      "label": "warning--railroad-crossing-with-barriers--g1",
      "bbox": {
        "xmin": 1518.7734375,
        "ymin": 1658.35546875,
        "xmax": 1550.015625,
        "ymax": 1689.345703125
      },
      "properties": {
        "barrier": false,
        "occluded": false,
        "out-of-frame": false,
        "exterior": false,
        "ambiguous": false,
        "included": false,
        "direction-or-information": false,
        "highway": false,
        "dummy": false
      }
    },
    {
      "key": "a3jy6z1yl8fmbp7m20hqzd",
      "label": "other-sign",
      "bbox": {
        "xmin": 3427.5703125,
        "ymin": 1288.740234375,
        "xmax": 3951.6328125,
        "ymax": 1606.95703125
      },
      "properties": {
        "barrier": false,
        "occluded": false,
        "out-of-frame": false,
        "exterior": false,
        "ambiguous": false,
        "included": false,
        "direction-or-information": true,
        "highway": false,
        "dummy": false
      }
    },
    {
      "key": "ruhw6r3m5zf2hbsmuy8soc",
      "label": "warning--railroad-crossing-with-barriers--g1",
      "bbox": {
        "xmin": 2419.7578125,
        "ymin": 1687.833984375,
        "xmax": 2453.015625,
        "ymax": 1718.82421875
      },
      "properties": {
        "barrier": false,
        "occluded": false,
        "out-of-frame": false,
        "exterior": false,
        "ambiguous": false,
        "included": false,
        "direction-or-information": false,
        "highway": false,
        "dummy": false
      }
    },
    {
      "key": "ge6fa21ywpisa6vxfhurhm",
      "label": "other-sign",
      "bbox": {
        "xmin": 2356.265625,
        "ymin": 1681.03125,
        "xmax": 2397.5859375,
        "ymax": 1697.66015625
      },
      "properties": {
        "barrier": false,
        "occluded": true,
        "out-of-frame": false,
        "exterior": false,
        "ambiguous": true,
        "included": false,
        "direction-or-information": false,
        "highway": false,
        "dummy": false
      }
    },
    {
      "key": "7npfyvxuxdcmgqkkbe9dbm",
      "label": "other-sign",
      "bbox": {
        "xmin": 2287.734375,
        "ymin": 1564.62890625,
        "xmax": 2331.0703125,
        "ymax": 1603.177734375
      },
      "properties": {
        "barrier": false,
        "occluded": true,
        "out-of-frame": false,
        "exterior": false,
        "ambiguous": true,
        "included": false,
        "direction-or-information": false,
        "highway": false,
        "dummy": false
      }
    },
    {
      "key": "ckrsbphzyt3qmepquvcxql",
      "label": "other-sign",
      "bbox": {
        "xmin": 2289.75,
        "ymin": 1661.37890625,
        "xmax": 2315.953125,
        "ymax": 1694.63671875
      },
      "properties": {
        "barrier": false,
        "occluded": true,
        "out-of-frame": false,
        "exterior": false,
        "ambiguous": true,
        "included": false,
        "direction-or-information": false,
        "highway": false,
        "dummy": false
      }
    },
    {
      "key": "dxkd0ozo2f1eqk2xndwxyx",
      "label": "other-sign",
      "bbox": {
        "xmin": 2332.078125,
        "ymin": 1710.509765625,
        "xmax": 2371.3828125,
        "ymax": 1758.884765625
      },
      "properties": {
        "barrier": false,
        "occluded": true,
        "out-of-frame": false,
        "exterior": false,
        "ambiguous": true,
        "included": false,
        "direction-or-information": false,
        "highway": false,
        "dummy": false
      }
    },
    {
      "key": "tbiljasjmm58k90oi51ov7",
      "label": "other-sign",
      "bbox": {
        "xmin": 2294.7890625,
        "ymin": 1606.201171875,
        "xmax": 2324.015625,
        "ymax": 1633.412109375
      },
      "properties": {
        "barrier": false,
        "occluded": true,
        "out-of-frame": false,
        "exterior": false,
        "ambiguous": true,
        "included": false,
        "direction-or-information": false,
        "highway": false,
        "dummy": false
      }
    },
    {
      "key": "7h0o22vcpem8i9d9w9cdzz",
      "label": "other-sign",
      "bbox": {
        "xmin": 2737.21875,
        "ymin": 1666.669921875,
        "xmax": 2788.6171875,
        "ymax": 1693.880859375
      },
      "properties": {
        "barrier": false,
        "occluded": false,
        "out-of-frame": false,
        "exterior": false,
        "ambiguous": false,
        "included": false,
        "direction-or-information": false,
        "highway": false,
        "dummy": false
      }
    }
  ]
}