{
  "width": 2448,
  "height": 2050,
  "ispano": false,
  "objects": [
    {
      "key": "8t7aixft2glrk5ls7xnu0l",
      "label": "other-sign",
      "bbox": {
        "xmin": 1629.2109375,
        "ymin": 1108.0810546875,
        "xmax": 1704.515625,
        "ymax": 1183.154296875
      },
      "properties": {
        "barrier": false,
        "occluded": false,
        "out-of-frame": false,
        "exterior": false,
        "ambiguous": false,
        "included": false,
        "direction-or-information": false,
        "highway": false,
        "dummy": false
      }
    }
  ]
}