{
  "width": 5312,
  "height": 2988,
  "ispano": false,
  "objects": [
    {
      "key": "aK6gWtVSRpyqftYdnQfi9Q",
      "label": "warning--height-restriction--g2",
      "bbox": {
        "xmin": 2600.234375,
        "ymin": 1444.39453125,
        "xmax": 2661.1875,
        "ymax": 1507.130859375
      },
      "properties": {
        "barrier": false,
        "occluded": false,
        "out-of-frame": false,
        "exterior": false,
        "ambiguous": false,
        "included": false,
        "direction-or-information": false,
        "highway": false,
        "dummy": false
      }
    },
    {
      "key": "P0fXt-MDQsKl2E8I9QLLcg",
      "label": "regulatory--no-parking--g2",
      "bbox": {
        "xmin": 2811.625,
        "ymin": 1503.4833984375,
        "xmax": 2841.453125,
        "ymax": 1531.93359375
      },
      "properties": {
        "barrier": false,
        "occluded": false,
        "out-of-frame": false,
        "exterior": false,
        "ambiguous": false,
        "included": false,
        "direction-or-information": false,
        "highway": false,
        "dummy": false
      }
    },
    {
      "key": "6wEbDB3GQcimZzo5WaoPSQ",
      "label": "regulatory--stop--g1",
      "bbox": {
        "xmin": 2689.71875,
        "ymin": 1426.1572265625,
        "xmax": 2742.890625,
        "ymax": 1480.1396484375
      },
      "properties": {
        "barrier": false,
        "occluded": false,
        "out-of-frame": false,
        "exterior": false,
        "ambiguous": false,
        "included": false,
        "direction-or-information": false,
        "highway": false,
        "dummy": false
      }
    },
    {
      "key": "86r9BsHcReC0nkdKyiamfw",
      "label": "other-sign",
      "bbox": {
        "xmin": 1436.9375,
        "ymin": 1218.9814453125,
        "xmax": 1562.734375,
        "ymax": 1251.80859375
      },
      "properties": {
        "barrier": false,
        "occluded": false,
        "out-of-frame": false,
        "exterior": false,
        "ambiguous": false,
        "included": false,
        "direction-or-information": true,
        "highway": false,
        "dummy": false
      }
    },
    {
      "key": "-F3nN_MhSmO1hCyLV5qszw",
      "label": "regulatory--maximum-speed-limit-25--g2",
      "bbox": {
        "xmin": 2515.9375,
        "ymin": 1485.9755859375,
        "xmax": 2532.796875,
        "ymax": 1509.3193359375
      },
      "properties": {
        "barrier": false,
        "occluded": false,
        "out-of-frame": false,
        "exterior": false,
        "ambiguous": false,
        "included": false,
        "direction-or-information": false,
        "highway": false,
        "dummy": false
      }
    },
    {
      "key": "A4TTexkdQDO8hNVm9qZJgQ",
      "label": "other-sign",
      "bbox": {
        "xmin": 2134.65625,
        "ymin": 1415.9443359375,
        "xmax": 2173.5625,
        "ymax": 1430.5341796875
      },
      "properties": {
        "barrier": false,
        "occluded": true,
        "out-of-frame": false,
        "exterior": false,
        "ambiguous": true,
        "included": false,
        "direction-or-information": false,
        "highway": false,
        "dummy": false
      }
    },
    {
      "key": "g2SixqdxQMmow0X9u7Zxow",
      "label": "other-sign",
      "bbox": {
        "xmin": 2619.6875,
        "ymin": 1507.8603515625,
        "xmax": 2650.8125,
        "ymax": 1525.3681640625
      },
      "properties": {
        "barrier": false,
        "occluded": false,
        "out-of-frame": false,
        "exterior": false,
        "ambiguous": false,
        "included": false,
        "direction-or-information": true,
        "highway": false,
        "dummy": false
      }
    },
    {
      "key": "uvH2EVmBSVmLJwCK6sIPwQ",
      "label": "other-sign",
      "bbox": {
        "xmin": 2706.578125,
        "ymin": 1479.41015625,
        "xmax": 2726.03125,
        "ymax": 1488.8935546875
      },
      "properties": {
        "barrier": false,
        "occluded": false,
        "out-of-frame": false,
        "exterior": false,
        "ambiguous": true,
        "included": false,
        "direction-or-information": false,
        "highway": false,
        "dummy": false
      }
    },
    {
      "key": "aeFQKc2YRDGsuJiP858YgQ",
      "label": "other-sign",
      "bbox": {
        "xmin": 2190.421875,
        "ymin": 1496.1884765625,
        "xmax": 2212.46875,
        "ymax": 1502.0244140625
      },
      "properties": {
        "barrier": false,
        "occluded": false,
        "out-of-frame": false,
        "exterior": false,
        "ambiguous": true,
        "included": false,
        "direction-or-information": false,
        "highway": false,
        "dummy": false
      }
    },
    {
      "key": "AwkbgBUdR-mHmNaQ-4UVZA",
      "label": "other-sign",
      "bbox": {
        "xmin": 2672.859375,
        "ymin": 1500.5654296875,
        "xmax": 2698.796875,
        "ymax": 1516.6142578125
      },
      "properties": {
        "barrier": false,
        "occluded": false,
        "out-of-frame": false,
        "exterior": false,
        "ambiguous": false,
        "included": false,
        "direction-or-information": true,
        "highway": false,
        "dummy": false
      }
    },
    {
      "key": "ubFwGw_TSsmaWhtWL4FelQ",
      "label": "other-sign",
      "bbox": {
        "xmin": 2675.453125,
        "ymin": 1457.525390625,
        "xmax": 2701.390625,
        "ymax": 1495.458984375
      },
      "properties": {
        "barrier": false,
        "occluded": true,
        "out-of-frame": false,
        "exterior": false,
        "ambiguous": true,
        "included": false,
        "direction-or-information": false,
        "highway": false,
        "dummy": false
      }
    }
  ]
}