{
  "width": 4160,
  "height": 3120,
  "ispano": false,
  "objects": [
    {
      "key": "RIyWK6rUTuWd8qCtT8Ei-Q",
      "label": "other-sign",
      "bbox": {
        "xmin": 2364.375,
        "ymin": 1409.94140625,
        "xmax": 2511.640625,
        "ymax": 1644.55078125
      },
      "properties": {
        "barrier": false,
        "occluded": false,
        "out-of-frame": false,
        "exterior": true,
        "ambiguous": false,
        "included": false,
        "direction-or-information": false,
        "highway": false,
        "dummy": false
      }
    },
    {
      "key": "ZOeflc7JQJufqVE3CzgHdA",
      "label": "warning--double-curve-first-right--g2",
      "bbox": {
        "xmin": 2385.703125,
        "ymin": 1471.640625,
        "xmax": 2490.3125,
        "ymax": 1576.7578125
      },
      "properties": {
        "barrier": false,
        "occluded": false,
        "out-of-frame": false,
        "exterior": false,
        "ambiguous": false,
        "included": true,
        "direction-or-information": false,
        "highway": false,
        "dummy": false
      }
    },
    {
      "key": "23NpTUoDRRCuVdVbXOtQUA",
      "label": "other-sign",
      "bbox": {
        "xmin": 660.15625,
        "ymin": 1343.671875,
        "xmax": 826.71875,
        "ymax": 1583.61328125
      },
      "properties": {
        "barrier": false,
        "occluded": false,
        "out-of-frame": false,
        "exterior": true,
        "ambiguous": false,
        "included": false,
        "direction-or-information": false,
        "highway": false,
        "dummy": false
      }
    },
    {
      "key": "MWVmTf5xQy2jGBfF6LO78g",
      "label": "warning--double-curve-first-right--g2",
      "bbox": {
        "xmin": 686.5625,
        "ymin": 1403.84765625,
        "xmax": 801.328125,
        "ymax": 1513.53515625
      },
      "properties": {
        "barrier": false,
        "occluded": false,
        "out-of-frame": false,
        "exterior": false,
        "ambiguous": false,
        "included": true,
        "direction-or-information": false,
        "highway": false,
        "dummy": false
      }
    },
    {
      "key": "-4sNsEQ0TWuRod1ycP67BQ",
      "label": "other-sign",
      "bbox": {
        "xmin": 2006.875,
        "ymin": 1570.6640625,
        "xmax": 2089.140625,
        "ymax": 1598.0859375
      },
      "properties": {
        "barrier": false,
        "occluded": false,
        "out-of-frame": false,
        "exterior": false,
        "ambiguous": true,
        "included": false,
        "direction-or-information": false,
        "highway": false,
        "dummy": false
      }
    }
  ]
}