{
  "width": 3968,
  "height": 2976,
  "ispano": false,
  "objects": [
    {
      "key": "oqbq5d5q96pbqg11wyndto",
      "label": "other-sign",
      "bbox": {
        "xmin": 1956.875,
        "ymin": 1988.6015625,
        "xmax": 1994.65625,
        "ymax": 2027.109375
      },
      "properties": {
        "barrier": false,
        "occluded": false,
        "out-of-frame": false,
        "exterior": false,
        "ambiguous": false,
        "included": false,
        "direction-or-information": false,
        "highway": false,
        "dummy": false
      }
    },
    {
      "key": "kq5d8zvy50awygli9lui3l",
      "label": "other-sign",
      "bbox": {
        "xmin": 1718.5625,
        "ymin": 2026.3828125,
        "xmax": 1740.84375,
        "ymax": 2040.9140625
      },
      "properties": {
        "barrier": false,
        "occluded": false,
        "out-of-frame": false,
        "exterior": false,
        "ambiguous": true,
        "included": false,
        "direction-or-information": false,
        "highway": false,
        "dummy": false
      }
    }
  ]
}