{
  "width": 3264,
  "height": 2448,
  "ispano": false,
  "objects": [
    {
      "key": "lar0qcuruhg5rfb3ntk00qrfbk",
      "label": "other-sign",
      "bbox": {
        "xmin": 2256.75,
        "ymin": 1031.5546875,
        "xmax": 2416.125,
        "ymax": 1209.65625
      },
      "properties": {
        "barrier": false,
        "occluded": false,
        "out-of-frame": false,
        "exterior": true,
        "ambiguous": false,
        "included": false,
        "direction-or-information": false,
        "highway": false,
        "dummy": false
      }
    },
    {
      "key": "m2bl4fft9q0ecmf6d3l3tp79re",
      "label": "regulatory--no-right-turn--g1",
      "bbox": {
        "xmin": 0.0,
        "ymin": 1317.83203125,
        "xmax": 105.1875,
        "ymax": 1422.421875
      },
      "properties": {
        "barrier": false,
        "occluded": false,
        "out-of-frame": false,
        "exterior": false,
        "ambiguous": false,
        "included": false,
        "direction-or-information": false,
        "highway": false,
        "dummy": false
      }
    },
    {
      "key": "n91ockav37pq9erqimk5qg478e",
      "label": "regulatory--no-parking--g2",
      "bbox": {
        "xmin": 1604.90625,
        "ymin": 1124.19140625,
        "xmax": 1755.515625,
        "ymax": 1293.328125
      },
      "properties": {
        "barrier": false,
        "occluded": false,
        "out-of-frame": false,
        "exterior": false,
        "ambiguous": false,
        "included": false,
        "direction-or-information": false,
        "highway": false,
        "dummy": false
      }
    },
    {
      "key": "60kf4qt3dflnrturm5tr75eoim",
      "label": "warning--height-restriction--g2",
      "bbox": {
        "xmin": 368.15625,
        "ymin": 1313.6484375,
        "xmax": 509.203125,
        "ymax": 1437.36328125
      },
      "properties": {
        "barrier": false,
        "occluded": false,
        "out-of-frame": false,
        "exterior": false,
        "ambiguous": false,
        "included": false,
        "direction-or-information": false,
        "highway": false,
        "dummy": false
      }
    },
    {
      "key": "5tcpckcp3n2oo0bg1m7an5ghnh",
      "label": "other-sign",
      "bbox": {
        "xmin": 654.234375,
        "ymin": 1303.48828125,
        "xmax": 754.640625,
        "ymax": 1409.87109375
      },
      "properties": {
        "barrier": false,
        "occluded": false,
        "out-of-frame": false,
        "exterior": true,
        "ambiguous": false,
        "included": false,
        "direction-or-information": false,
        "highway": false,
        "dummy": false
      }
    }
  ]
}