{
  "width": 3264,
  "height": 2448,
  "ispano": false,
  "objects": [
    {
      "key": "Qf1_6tvnQZmYghVj9bDA0w",
      "label": "regulatory--yield--g1",
      "bbox": {
        "xmin": 310.78125,
        "ymin": 1285.55859375,
        "xmax": 339.46875,
        "ymax": 1316.63671875
      },
      "properties": {
        "barrier": false,
        "occluded": false,
        "out-of-frame": false,
        "exterior": false,
        "ambiguous": false,
        "included": false,
        "direction-or-information": false,
        "highway": false,
        "dummy": false
      }
    }
  ]
}