{
  "width": 4128,
  "height": 3096,
  "ispano": false,
  "objects": [
    {
      "key": "lc0k4ckuds6krpy7db05mm",
      "label": "other-sign",
      "bbox": {
        "xmin": 1924.921875,
        "ymin": 2085.416015625,
        "xmax": 1938.0234375,
        "ymax": 2105.068359375
      },
      "properties": {
        "barrier": false,
        "occluded": false,
        "out-of-frame": false,
        "exterior": false,
        "ambiguous": true,
        "included": false,
        "direction-or-information": false,
        "highway": false,
        "dummy": false
      }
    },
    {
      "key": "qoffozmjclfcla3cj55j9z",
      "label": "other-sign",
      "bbox": {
        "xmin": 1721.34375,
        "ymin": 2083.904296875,
        "xmax": 1733.4375,
        "ymax": 2103.556640625
      },
      "properties": {
        "barrier": false,
        "occluded": false,
        "out-of-frame": false,
        "exterior": false,
        "ambiguous": true,
        "included": false,
        "direction-or-information": false,
        "highway": false,
        "dummy": false
      }
    }
  ]
}