{
  "width": 5312,
  "height": 2988,
  "ispano": false,
  "objects": [
    {
      "key": "e8jj4d3m88w7hpmg10cni0",
      "label": "regulatory--maximum-speed-limit-60--g1",
      "bbox": {
        "xmin": 2445.90625,
        "ymin": 1736.19140625,
        "xmax": 2465.359375,
        "ymax": 1760.994140625
      },
      "properties": {
        "barrier": false,
        "occluded": false,
        "out-of-frame": false,
        "exterior": false,
        "ambiguous": false,
        "included": false,
        "direction-or-information": false,
        "highway": false,
        "dummy": false
      }
    },
    {
      "key": "u1ql5qs9khjbgd6o8xsr3l",
      "label": "regulatory--no-u-turn--g3",
      "bbox": {
        "xmin": 3373.171875,
        "ymin": 2014.857421875,
        "xmax": 3528.796875,
        "ymax": 2174.6162109375
      },
      "properties": {
        "barrier": false,
        "occluded": false,
        "out-of-frame": false,
        "exterior": false,
        "ambiguous": false,
        "included": false,
        "direction-or-information": false,
        "highway": false,
        "dummy": false
      }
    },
    {
      "key": "5cikijdee1cc7w3yrsd04p",
      "label": "regulatory--no-heavy-goods-vehicles--g4",
      "bbox": {
        "xmin": 587.484375,
        "ymin": 1455.3369140625,
        "xmax": 679.5625,
        "ymax": 1550.1708984375
      },
      "properties": {
        "barrier": false,
        "occluded": false,
        "out-of-frame": false,
        "exterior": false,
        "ambiguous": false,
        "included": false,
        "direction-or-information": false,
        "highway": false,
        "dummy": false
      }
    },
    {
      "key": "a8r7yuokfklih4je69qvyo",
      "label": "other-sign",
      "bbox": {
        "xmin": 1434.34375,
        "ymin": 1542.8759765625,
        "xmax": 1580.890625,
        "ymax": 1574.9736328125
      },
      "properties": {
        "barrier": false,
        "occluded": false,
        "out-of-frame": false,
        "exterior": false,
        "ambiguous": false,
        "included": false,
        "direction-or-information": true,
        "highway": false,
        "dummy": false
      }
    },
    {
      "key": "n7j1c0st46cezo0bea2w8a",
      "label": "other-sign",
      "bbox": {
        "xmin": 1832.484375,
        "ymin": 1644.275390625,
        "xmax": 1885.65625,
        "ymax": 1680.75
      },
      "properties": {
        "barrier": false,
        "occluded": false,
        "out-of-frame": false,
        "exterior": false,
        "ambiguous": false,
        "included": false,
        "direction-or-information": false,
        "highway": false,
        "dummy": false
      }
    },
    {
      "key": "j5ubkkm2kqdm4gb1ktcow4",
      "label": "other-sign",
      "bbox": {
        "xmin": 1835.078125,
        "ymin": 1577.162109375,
        "xmax": 1888.25,
        "ymax": 1645.0048828125
      },
      "properties": {
        "barrier": false,
        "occluded": false,
        "out-of-frame": false,
        "exterior": false,
        "ambiguous": false,
        "included": false,
        "direction-or-information": false,
        "highway": false,
        "dummy": false
      }
    }
  ]
}