{
  "width": 3264,
  "height": 1836,
  "ispano": false,
  "objects": [
    {
      "key": "pror8znmc2c323hr8q1g95",
      "label": "regulatory--no-heavy-goods-vehicles--g1",
      "bbox": {
        "xmin": 1234.359375,
        "ymin": 689.396484375,
        "xmax": 1256.671875,
        "ymax": 738.703125
      },
      "properties": {
        "barrier": false,
        "occluded": false,
        "out-of-frame": false,
        "exterior": false,
        "ambiguous": false,
        "included": false,
        "direction-or-information": false,
        "highway": false,
        "dummy": false
      }
    },
    {
      "key": "xoml863ut0v1mflxdzl8xc",
      "label": "information--parking--g1",
      "bbox": {
        "xmin": 1484.578125,
        "ymin": 819.8349609375,
        "xmax": 1494.9375,
        "ymax": 830.14453125
      },
      "properties": {
        "barrier": false,
        "occluded": false,
        "out-of-frame": false,
        "exterior": false,
        "ambiguous": false,
        "included": false,
        "direction-or-information": false,
        "highway": false,
        "dummy": true
      }
    },
    {
      "key": "ijf47gu22g3u2k81b4qnp1",
      "label": "other-sign",
      "bbox": {
        "xmin": 2090.203125,
        "ymin": 330.802734375,
        "xmax": 2121.28125,
        "ymax": 360.38671875
      },
      "properties": {
        "barrier": false,
        "occluded": false,
        "out-of-frame": false,
        "exterior": false,
        "ambiguous": true,
        "included": true,
        "direction-or-information": false,
        "highway": false,
        "dummy": false
      }
    },
    {
      "key": "u4jzbo0e6oe6g4tne2urbn",
      "label": "other-sign",
      "bbox": {
        "xmin": 2397.0,
        "ymin": 612.298828125,
        "xmax": 2517.328125,
        "ymax": 770.9765625
      },
      "properties": {
        "barrier": false,
        "occluded": false,
        "out-of-frame": false,
        "exterior": false,
        "ambiguous": false,
        "included": false,
        "direction-or-information": false,
        "highway": false,
        "dummy": false
      }
    },
    {
      "key": "c311npxwxsu3y39lt2jeww",
      "label": "other-sign",
      "bbox": {
        "xmin": 1937.203125,
        "ymin": 741.392578125,
        "xmax": 1950.75,
        "ymax": 757.0810546875
      },
      "properties": {
        "barrier": false,
        "occluded": false,
        "out-of-frame": false,
        "exterior": false,
        "ambiguous": true,
        "included": false,
        "direction-or-information": false,
        "highway": false,
        "dummy": false
      }
    },
    {
      "key": "lf0xlde2j9dc9dyprru5iv",
      "label": "other-sign",
      "bbox": {
        "xmin": 3150.046875,
        "ymin": 558.509765625,
        "xmax": 3263.203125,
        "ymax": 730.1865234375
      },
      "properties": {
        "barrier": false,
        "occluded": false,
        "out-of-frame": true,
        "exterior": false,
        "ambiguous": true,
        "included": false,
        "direction-or-information": false,
        "highway": false,
        "dummy": false
      }
    },
    {
      "key": "2hpst0u8exw37l3uzdca1x",
      "label": "complementary--go-left--g1",
      "bbox": {
        "xmin": 3133.3125,
        "ymin": 435.69140625,
        "xmax": 3263.203125,
        "ymax": 555.3720703125
      },
      "properties": {
        "barrier": false,
        "occluded": false,
        "out-of-frame": true,
        "exterior": false,
        "ambiguous": false,
        "included": false,
        "direction-or-information": false,
        "highway": false,
        "dummy": false
      }
    },
    {
      "key": "ms7clvzlaq7rf2iacg4vup",
      "label": "other-sign",
      "bbox": {
        "xmin": 3118.171875,
        "ymin": 312.4248046875,
        "xmax": 3263.203125,
        "ymax": 438.8291015625
      },
      "properties": {
        "barrier": false,
        "occluded": false,
        "out-of-frame": true,
        "exterior": false,
        "ambiguous": true,
        "included": false,
        "direction-or-information": false,
        "highway": false,
        "dummy": false
      }
    },
    {
      "key": "7gu8ytkay8bonmfo29gu3t",
      "label": "other-sign",
      "bbox": {
        "xmin": 2003.34375,
        "ymin": 37.2041015625,
        "xmax": 2284.640625,
        "ymax": 450.931640625
      },
      "properties": {
        "barrier": false,
        "occluded": false,
        "out-of-frame": false,
        "exterior": false,
        "ambiguous": false,
        "included": false,
        "direction-or-information": true,
        "highway": false,
        "dummy": false
      }
    },
    {
      "key": "brlxw6cw3ftbiotk59cvde",
      "label": "regulatory--no-parking--g1",
      "bbox": {
        "xmin": 2353.171875,
        "ymin": 601.0927734375,
        "xmax": 2432.859375,
        "ymax": 682.6728515625
      },
      "properties": {
        "barrier": false,
        "occluded": true,
        "out-of-frame": false,
        "exterior": false,
        "ambiguous": false,
        "included": false,
        "direction-or-information": false,
        "highway": false,
        "dummy": false
      }
    },
    {
      "key": "q9y7srh4afdydr688ml9mv",
      "label": "information--emergency-facility--g2",
      "bbox": {
        "xmin": 2076.65625,
        "ymin": 150.609375,
        "xmax": 2105.34375,
        "ymax": 182.4345703125
      },
      "properties": {
        "barrier": false,
        "occluded": false,
        "out-of-frame": false,
        "exterior": false,
        "ambiguous": false,
        "included": true,
        "direction-or-information": false,
        "highway": false,
        "dummy": false
      }
    },
    {
      "key": "f1ndj52liyx079ck3330ui",
      "label": "information--pedestrians-crossing--g1",
      "bbox": {
        "xmin": 1810.5,
        "ymin": 512.3408203125,
        "xmax": 1871.0625,
        "ymax": 570.6123046875
      },
      "properties": {
        "barrier": false,
        "occluded": false,
        "out-of-frame": false,
        "exterior": false,
        "ambiguous": false,
        "included": false,
        "direction-or-information": false,
        "highway": false,
        "dummy": false
      }
    },
    {
      "key": "rasd23f5mjvgtkedod493h",
      "label": "other-sign",
      "bbox": {
        "xmin": 2079.046875,
        "ymin": 194.9853515625,
        "xmax": 2254.359375,
        "ymax": 243.84375
      },
      "properties": {
        "barrier": false,
        "occluded": false,
        "out-of-frame": false,
        "exterior": false,
        "ambiguous": false,
        "included": true,
        "direction-or-information": false,
        "highway": false,
        "dummy": false
      }
    },
    {
      "key": "p5z3eyds5ge7avpxhl3e5j",
      "label": "regulatory--no-heavy-goods-vehicles--g1",
      "bbox": {
        "xmin": 3107.8125,
        "ymin": 89.2001953125,
        "xmax": 3263.203125,
        "ymax": 311.9765625
      },
      "properties": {
        "barrier": false,
        "occluded": false,
        "out-of-frame": true,
        "exterior": false,
        "ambiguous": false,
        "included": false,
        "direction-or-information": false,
        "highway": false,
        "dummy": false
      }
    },
    {
      "key": "wci75w4tk45dyr9s5qejbs",
      "label": "information--pedestrians-crossing--g1",
      "bbox": {
        "xmin": 2076.65625,
        "ymin": 679.9833984375,
        "xmax": 2138.015625,
        "ymax": 742.7373046875
      },
      "properties": {
        "barrier": false,
        "occluded": true,
        "out-of-frame": false,
        "exterior": false,
        "ambiguous": false,
        "included": false,
        "direction-or-information": false,
        "highway": false,
        "dummy": false
      }
    },
    {
      "key": "ghegebdx6ytp6f652qqkub",
      "label": "regulatory--no-parking--g1",
      "bbox": {
        "xmin": 2027.25,
        "ymin": 748.564453125,
        "xmax": 2059.125,
        "ymax": 778.1484375
      },
      "properties": {
        "barrier": false,
        "occluded": false,
        "out-of-frame": false,
        "exterior": false,
        "ambiguous": false,
        "included": false,
        "direction-or-information": false,
        "highway": false,
        "dummy": false
      }
    },
    {
      "key": "7l7q41s44judbextd8jfng",
      "label": "other-sign",
      "bbox": {
        "xmin": 1235.15625,
        "ymin": 734.6689453125,
        "xmax": 1260.65625,
        "ymax": 766.9423828125
      },
      "properties": {
        "barrier": false,
        "occluded": false,
        "out-of-frame": false,
        "exterior": false,
        "ambiguous": true,
        "included": false,
        "direction-or-information": false,
        "highway": false,
        "dummy": false
      }
    },
    {
      "key": "b54zy4gwsw73zikv28y01z",
      "label": "other-sign",
      "bbox": {
        "xmin": 1236.75,
        "ymin": 766.494140625,
        "xmax": 1261.453125,
        "ymax": 806.3876953125
      },
      "properties": {
        "barrier": false,
        "occluded": false,
        "out-of-frame": false,
        "exterior": false,
        "ambiguous": true,
        "included": false,
        "direction-or-information": false,
        "highway": false,
        "dummy": false
      }
    }
  ]
}