{
  "width": 3984,
  "height": 2988,
  "ispano": false,
  "objects": [
    {
      "key": "ul6nvyedkmdbbrzsqji6q1",
      "label": "other-sign",
      "bbox": {
        "xmin": 2858.63671875,
        "ymin": 1550.900390625,
        "xmax": 2974.3828125,
        "ymax": 1640.6279296875
      },
      "properties": {
        "barrier": false,
        "occluded": false,
        "out-of-frame": false,
        "exterior": false,
        "ambiguous": false,
        "included": false,
        "direction-or-information": false,
        "highway": true,
        "dummy": false
      }
    },
    {
      "key": "wnhbu1g7y18z2ac9sp62x0",
      "label": "regulatory--no-entry--g1",
      "bbox": {
        "xmin": 1271.26171875,
        "ymin": 1804.763671875,
        "xmax": 1289.7421875,
        "ymax": 1824.4599609375
      },
      "properties": {
        "barrier": false,
        "occluded": false,
        "out-of-frame": false,
        "exterior": false,
        "ambiguous": false,
        "included": false,
        "direction-or-information": false,
        "highway": false,
        "dummy": false
      }
    },
    {
      "key": "pkrriz01iuokuwrnhgqasz",
      "label": "warning--road-narrows-right--g2",
      "bbox": {
        "xmin": 2174.859375,
        "ymin": 1698.9873046875,
        "xmax": 2226.41015625,
        "ymax": 1748.5927734375
      },
      "properties": {
        "barrier": false,
        "occluded": false,
        "out-of-frame": false,
        "exterior": false,
        "ambiguous": false,
        "included": false,
        "direction-or-information": false,
        "highway": false,
        "dummy": false
      }
    },
    {
      "key": "jcacm94qkjrop63131moqp",
      "label": "regulatory--maximum-speed-limit-45--g3",
      "bbox": {
        "xmin": 2310.05859375,
        "ymin": 1661.783203125,
        "xmax": 2348.96484375,
        "ymax": 1707.7412109375
      },
      "properties": {
        "barrier": false,
        "occluded": false,
        "out-of-frame": false,
        "exterior": false,
        "ambiguous": false,
        "included": false,
        "direction-or-information": false,
        "highway": false,
        "dummy": false
      }
    },
    {
      "key": "eyuintct8yreuqh2vdg1j2",
      "label": "other-sign",
      "bbox": {
        "xmin": 2865.4453125,
        "ymin": 1507.130859375,
        "xmax": 2957.84765625,
        "ymax": 1553.818359375
      },
      "properties": {
        "barrier": false,
        "occluded": false,
        "out-of-frame": false,
        "exterior": false,
        "ambiguous": false,
        "included": false,
        "direction-or-information": false,
        "highway": false,
        "dummy": false
      }
    },
    {
      "key": "aiw0ag81rj3jjxt1w51g66",
      "label": "regulatory--keep-right--g4",
      "bbox": {
        "xmin": 1784.82421875,
        "ymin": 1772.666015625,
        "xmax": 1801.359375,
        "ymax": 1792.3623046875
      },
      "properties": {
        "barrier": false,
        "occluded": false,
        "out-of-frame": false,
        "exterior": false,
        "ambiguous": false,
        "included": false,
        "direction-or-information": false,
        "highway": false,
        "dummy": false
      }
    },
    {
      "key": "6warjnyfoi3m5s4ngbr9rn",
      "label": "regulatory--no-entry--g1",
      "bbox": {
        "xmin": 1652.54296875,
        "ymin": 1764.6416015625,
        "xmax": 1671.0234375,
        "ymax": 1787.255859375
      },
      "properties": {
        "barrier": false,
        "occluded": false,
        "out-of-frame": false,
        "exterior": false,
        "ambiguous": false,
        "included": false,
        "direction-or-information": false,
        "highway": false,
        "dummy": false
      }
    }
  ]
}