{
  "width": 3360,
  "height": 2240,
  "ispano": false,
  "objects": [
    {
      "key": "wyt2pwvmrf5ilj305xou6q",
      "label": "other-sign",
      "bbox": {
        "xmin": 535.6640625,
        "ymin": 1114.53125,
        "xmax": 564.375,
        "ymax": 1158.828125
      },
      "properties": {
        "barrier": false,
        "occluded": false,
        "out-of-frame": false,
        "exterior": false,
        "ambiguous": false,
        "included": false,
        "direction-or-information": false,
        "highway": false,
        "dummy": true
      }
    },
    {
      "key": "c13qnrctmntqxb8d90bn6x",
      "label": "other-sign",
      "bbox": {
        "xmin": 849.84375,
        "ymin": 977.8125,
        "xmax": 873.6328125,
        "ymax": 1012.265625
      },
      "properties": {
        "barrier": false,
        "occluded": false,
        "out-of-frame": false,
        "exterior": true,
        "ambiguous": false,
        "included": false,
        "direction-or-information": false,
        "highway": false,
        "dummy": true
      }
    },
    {
      "key": "4zm5shkpxpznut6k93eand",
      "label": "other-sign",
      "bbox": {
        "xmin": 230.5078125,
        "ymin": 714.765625,
        "xmax": 272.34375,
        "ymax": 750.859375
      },
      "properties": {
        "barrier": false,
        "occluded": false,
        "out-of-frame": false,
        "exterior": false,
        "ambiguous": false,
        "included": true,
        "direction-or-information": false,
        "highway": false,
        "dummy": true
      }
    },
    {
      "key": "ydpn92ugjgvwu8a5mfceoc",
      "label": "other-sign",
      "bbox": {
        "xmin": 538.125,
        "ymin": 1120.0,
        "xmax": 561.9140625,
        "ymax": 1142.421875
      },
      "properties": {
        "barrier": false,
        "occluded": false,
        "out-of-frame": false,
        "exterior": false,
        "ambiguous": false,
        "included": true,
        "direction-or-information": false,
        "highway": false,
        "dummy": true
      }
    },
    {
      "key": "xj09w27yuofrbhyj6g8xa4",
      "label": "other-sign",
      "bbox": {
        "xmin": 852.3046875,
        "ymin": 980.0,
        "xmax": 871.9921875,
        "ymax": 999.6875
      },
      "properties": {
        "barrier": false,
        "occluded": false,
        "out-of-frame": false,
        "exterior": false,
        "ambiguous": false,
        "included": true,
        "direction-or-information": false,
        "highway": false,
        "dummy": true
      }
    },
    {
      "key": "ctf4fh4h56hus40hzxj6m9",
      "label": "other-sign",
      "bbox": {
        "xmin": 226.40625,
        "ymin": 712.03125,
        "xmax": 275.625,
        "ymax": 771.640625
      },
      "properties": {
        "barrier": false,
        "occluded": false,
        "out-of-frame": false,
        "exterior": false,
        "ambiguous": false,
        "included": false,
        "direction-or-information": false,
        "highway": false,
        "dummy": true
      }
    },
    {
      "key": "i7zr5n1xilpv58ryil2fwe",
      "label": "other-sign",
      "bbox": {
        "xmin": 1137.7734375,
        "ymin": 890.3125,
        "xmax": 1151.71875,
        "ymax": 918.75
      },
      "properties": {
        "barrier": false,
        "occluded": false,
        "out-of-frame": false,
        "exterior": false,
        "ambiguous": true,
        "included": true,
        "direction-or-information": false,
        "highway": false,
        "dummy": true
      }
    },
    {
      "key": "z2kzzk81m2f9ar3m5i4aco",
      "label": "other-sign",
      "bbox": {
        "xmin": 1133.671875,
        "ymin": 880.46875,
        "xmax": 1154.1796875,
        "ymax": 938.4375
      },
      "properties": {
        "barrier": false,
        "occluded": false,
        "out-of-frame": false,
        "exterior": false,
        "ambiguous": false,
        "included": false,
        "direction-or-information": false,
        "highway": false,
        "dummy": true
      }
    }
  ]
}