{
  "width": 3264,
  "height": 2448,
  "ispano": false,
  "objects": [
    {
      "key": "xfcb7j6a3gc5n2ko02fnkb",
      "label": "other-sign",
      "bbox": {
        "xmin": 1192.921875,
        "ymin": 1296.9140625,
        "xmax": 1211.25,
        "ymax": 1321.41796875
      },
      "properties": {
        "barrier": false,
        "occluded": false,
        "out-of-frame": false,
        "exterior": false,
        "ambiguous": true,
        "included": false,
        "direction-or-information": false,
        "highway": false,
        "dummy": false
      }
    },
    {
      "key": "3f98fkkgoncij0xq3lct61",
      "label": "other-sign",
      "bbox": {
        "xmin": 1428.796875,
        "ymin": 1306.4765625,
        "xmax": 1448.71875,
        "ymax": 1333.37109375
      },
      "properties": {
        "barrier": false,
        "occluded": false,
        "out-of-frame": false,
        "exterior": false,
        "ambiguous": true,
        "included": false,
        "direction-or-information": false,
        "highway": false,
        "dummy": false
      }
    }
  ]
}