{
  "width": 1920,
  "height": 1080,
  "ispano": false,
  "objects": [
    {
      "key": "g4y583cvdc64qvkzjr3lp5",
      "label": "warning--railroad-crossing--g3",
      "bbox": {
        "xmin": 1409.0625,
        "ymin": 426.62109375,
        "xmax": 1457.34375,
        "ymax": 471.708984375
      },
      "properties": {
        "barrier": false,
        "occluded": false,
        "out-of-frame": false,
        "exterior": false,
        "ambiguous": false,
        "included": false,
        "direction-or-information": false,
        "highway": false,
        "dummy": false
      }
    },
    {
      "key": "svfgmu693f6vmjfhkb0eso",
      "label": "regulatory--stop--g1",
      "bbox": {
        "xmin": 1409.0625,
        "ymin": 384.169921875,
        "xmax": 1451.71875,
        "ymax": 425.56640625
      },
      "properties": {
        "barrier": false,
        "occluded": false,
        "out-of-frame": false,
        "exterior": false,
        "ambiguous": false,
        "included": false,
        "direction-or-information": false,
        "highway": false,
        "dummy": false
      }
    },
    {
      "key": "jotnamf44hye3qtnwgbyrk",
      "label": "other-sign",
      "bbox": {
        "xmin": 1417.96875,
        "ymin": 271.845703125,
        "xmax": 1492.96875,
        "ymax": 344.8828125
      },
      "properties": {
        "barrier": false,
        "occluded": false,
        "out-of-frame": false,
        "exterior": false,
        "ambiguous": false,
        "included": false,
        "direction-or-information": false,
        "highway": false,
        "dummy": false
      }
    },
    {
      "key": "zjxticohoavzs34jthsbv5",
      "label": "information--disabled-persons--g1",
      "bbox": {
        "xmin": 494.53125,
        "ymin": 567.421875,
        "xmax": 511.875,
        "ymax": 589.5703125
      },
      "properties": {
        "barrier": false,
        "occluded": false,
        "out-of-frame": false,
        "exterior": false,
        "ambiguous": false,
        "included": false,
        "direction-or-information": false,
        "highway": false,
        "dummy": true
      }
    }
  ]
}